{"chunk_definitions":[{"row":25,"row_count":1,"visible":true,"expansion_state":0,"options":{"engine":"r","echo":false,"label":"unnamed-chunk-137"},"document_id":"6452DCD7","chunk_id":"czxx98l61w564","chunk_label":"unnamed-chunk-1"},{"row":31,"row_count":1,"visible":true,"expansion_state":0,"options":{"engine":"r","echo":false,"label":"unnamed-chunk-138"},"document_id":"6452DCD7","chunk_id":"co8tt79r44y90","chunk_label":"unnamed-chunk-2"},{"row":44,"row_count":1,"visible":true,"expansion_state":0,"options":{"engine":"r","label":"unnamed-chunk-139"},"document_id":"6452DCD7","chunk_id":"cdviwvcwrumi4","chunk_label":"unnamed-chunk-3"},{"row":56,"row_count":1,"visible":true,"expansion_state":0,"options":{"engine":"r","label":"unnamed-chunk-140"},"document_id":"6452DCD7","chunk_id":"c3c6m8wtyznc8","chunk_label":"unnamed-chunk-4"},{"row":69,"row_count":1,"visible":true,"expansion_state":0,"options":{"engine":"r","label":"unnamed-chunk-141"},"document_id":"6452DCD7","chunk_id":"chtmj8smba5z1","chunk_label":"unnamed-chunk-5"},{"row":80,"row_count":1,"visible":true,"expansion_state":0,"options":{"engine":"r","label":"unnamed-chunk-142"},"document_id":"6452DCD7","chunk_id":"cmjo2xhxjgdqa","chunk_label":"unnamed-chunk-6"},{"row":92,"row_count":1,"visible":true,"expansion_state":0,"options":{"engine":"r","label":"unnamed-chunk-143"},"document_id":"6452DCD7","chunk_id":"c8hwbr6tjwmgv","chunk_label":"unnamed-chunk-7"},{"row":98,"row_count":1,"visible":true,"expansion_state":0,"options":{"engine":"r","label":"unnamed-chunk-144"},"document_id":"6452DCD7","chunk_id":"cnn2jnshezle2","chunk_label":"unnamed-chunk-8"},{"row":103,"row_count":1,"visible":true,"expansion_state":0,"options":{"engine":"r","label":"unnamed-chunk-145"},"document_id":"6452DCD7","chunk_id":"c21t7bsf1y78a","chunk_label":"unnamed-chunk-9"},{"row":110,"row_count":1,"visible":true,"expansion_state":0,"options":{"engine":"r","label":"unnamed-chunk-146"},"document_id":"6452DCD7","chunk_id":"ctup8hycul41d","chunk_label":"unnamed-chunk-10"},{"row":118,"row_count":1,"visible":true,"expansion_state":0,"options":{"engine":"r","label":"unnamed-chunk-147"},"document_id":"6452DCD7","chunk_id":"cvm2qi9ncwtjo","chunk_label":"unnamed-chunk-11"},{"row":170,"row_count":1,"visible":true,"expansion_state":0,"options":{"engine":"r","label":"unnamed-chunk-148"},"document_id":"6452DCD7","chunk_id":"cgw0muyuyzwr1","chunk_label":"unnamed-chunk-12"},{"row":245,"row_count":1,"visible":true,"expansion_state":0,"options":{"engine":"r","label":"unnamed-chunk-149"},"document_id":"6452DCD7","chunk_id":"c9igi3l9dnq91","chunk_label":"unnamed-chunk-13"},{"row":286,"row_count":1,"visible":true,"expansion_state":0,"options":{"engine":"r","label":"unnamed-chunk-150"},"document_id":"6452DCD7","chunk_id":"ckbbkoxa9f0gp","chunk_label":"unnamed-chunk-14"},{"row":322,"row_count":1,"visible":true,"expansion_state":0,"options":{"engine":"r","label":"unnamed-chunk-151"},"document_id":"6452DCD7","chunk_id":"cxoug0tl7pq9m","chunk_label":"unnamed-chunk-15"},{"row":351,"row_count":1,"visible":true,"expansion_state":0,"options":{"engine":"r","label":"unnamed-chunk-152"},"document_id":"6452DCD7","chunk_id":"c5zjgue5nifyu","chunk_label":"unnamed-chunk-16"},{"row":384,"row_count":1,"visible":true,"expansion_state":0,"options":{"engine":"r","label":"unnamed-chunk-153"},"document_id":"6452DCD7","chunk_id":"cxp2dbex7slkd","chunk_label":"unnamed-chunk-17"},{"row":464,"row_count":1,"visible":true,"expansion_state":0,"options":{"engine":"r","label":"unnamed-chunk-154"},"document_id":"6452DCD7","chunk_id":"csx5u048151gy","chunk_label":"unnamed-chunk-18"},{"row":494,"row_count":1,"visible":true,"expansion_state":0,"options":{"engine":"r","label":"unnamed-chunk-155"},"document_id":"6452DCD7","chunk_id":"ckowed99w9lt1","chunk_label":"unnamed-chunk-19"},{"row":522,"row_count":1,"visible":true,"expansion_state":0,"options":{"engine":"r","label":"unnamed-chunk-156"},"document_id":"6452DCD7","chunk_id":"c2gzs2f8dlewg","chunk_label":"unnamed-chunk-20"},{"row":557,"row_count":1,"visible":true,"expansion_state":0,"options":{"engine":"r","label":"unnamed-chunk-157"},"document_id":"6452DCD7","chunk_id":"carkby1z9yf0x","chunk_label":"unnamed-chunk-21"},{"row":582,"row_count":1,"visible":true,"expansion_state":0,"options":{"engine":"r","label":"unnamed-chunk-158"},"document_id":"6452DCD7","chunk_id":"cxu4yonl7ymh3","chunk_label":"unnamed-chunk-22"},{"row":590,"row_count":1,"visible":true,"expansion_state":0,"options":{"engine":"r","label":"unnamed-chunk-159"},"document_id":"6452DCD7","chunk_id":"ctkyhtox0jkxc","chunk_label":"unnamed-chunk-23"}],"doc_write_time":1698957038}